boltztest/__init__.py
boltztest/example.py
boltztest-0.0.1.dist-info/METADATA
boltztest-0.0.1.dist-info/WHEEL
boltztest-0.0.1.dist-info/licenses/LICENSE
boltztest-0.0.1.dist-info/RECORD
